{
  "Rating:": "PG-13 (Language|Intense Sequences of Action|Suggestive Material)",
  "Genre:": "Fantasy, Action, Adventure, Comedy",
  "Original Language:": "English",
  "Director:": "David F. Sandberg",
  "Producer:": "Peter Safran",
  "Writer:": "Henry Gayden",
  "Release Date (Theaters):": "Apr 5, 2019 wide",
  "Release Date (Streaming):": "Jul 2, 2019",
  "Box Office (Gross USA):": "$140.4M",
  "Runtime:": "2h 12m",
  "Distributor:": "Warner Bros. Pictures",
  "Sound Mix:": "Dolby Atmos",
  "Aspect Ratio:": "Scope (2.35:1)",
  "View the collection:": "DC Extended Universe",
  "Name:": "Shazam!"
}